rosy/__init__.py
rosy/__main__.py
rosy/argparse.py
rosy/asyncio.py
rosy/cli/__init__.py
rosy/cli/bag/__init__.py
rosy/cli/bag/file.py
rosy/cli/bag/info.py
rosy/cli/bag/main.py
rosy/cli/bag/play.py
rosy/cli/bag/record.py
rosy/cli/launch/__init__.py
rosy/cli/launch/args.py
rosy/cli/launch/config.py
rosy/cli/launch/main.py
rosy/cli/main.py
rosy/cli/node/__init__.py
rosy/cli/node/list.py
rosy/cli/node/main.py
rosy/cli/service/__init__.py
rosy/cli/service/call.py
rosy/cli/service/list.py
rosy/cli/service/main.py
rosy/cli/speedtest.py
rosy/cli/topic/__init__.py
rosy/cli/topic/echo.py
rosy/cli/topic/list.py
rosy/cli/topic/main.py
rosy/cli/topic/send.py
rosy/cli/utils.py
rosy/codec.py
rosy/demo/__init__.py
rosy/demo/launch.yaml
rosy/demo/service_caller.py
rosy/demo/service_provider.py
rosy/demo/topic_listener.py
rosy/demo/topic_sender.py
rosy/discovery/__init__.py
rosy/discovery/base.py
rosy/discovery/zeroconf.py
rosy/network.py
rosy/node/__init__.py
rosy/node/builder.py
rosy/node/callbackmanager.py
rosy/node/clienthandler.py
rosy/node/codec.py
rosy/node/loadbalancing.py
rosy/node/node.py
rosy/node/peer/__init__.py
rosy/node/peer/connection.py
rosy/node/peer/selector.py
rosy/node/servers.py
rosy/node/service/__init__.py
rosy/node/service/caller.py
rosy/node/service/codec.py
rosy/node/service/handlermanager.py
rosy/node/service/requesthandler.py
rosy/node/service/types.py
rosy/node/topic/__init__.py
rosy/node/topic/codec.py
rosy/node/topic/listenermanager.py
rosy/node/topic/messagehandler.py
rosy/node/topic/outbox.py
rosy/node/topic/sender.py
rosy/node/topic/types.py
rosy/node/topology.py
rosy/node/types.py
rosy/procman.py
rosy/socket.py
rosy/specs.py
rosy/types.py
rosy/utils.py
rosy/version.py
rosy-0.8.3.dist-info/LICENSE
rosy-0.8.3.dist-info/METADATA
rosy-0.8.3.dist-info/WHEEL
rosy-0.8.3.dist-info/entry_points.txt
rosy-0.8.3.dist-info/RECORD
