Metadata-Version: 2.3
Name: rosy
Version: 0.8.3
Summary: It's not ROS, but it is ROS-y! Simple, fast inter-process message passing for distributed Python processes
License: MIT
Author: Austin Bowen
Author-email: austin.bowen.314@gmail.com
Requires-Python: <4,>=3.10
Classifier: License :: OSI Approved :: MIT License
Classifier: Programming Language :: Python :: 3
Classifier: Programming Language :: Python :: 3.10
Classifier: Programming Language :: Python :: 3.11
Classifier: Programming Language :: Python :: 3.12
Classifier: Programming Language :: Python :: 3.13
Requires-Dist: PyYAML
Requires-Dist: msgpack
Requires-Dist: orjson
Requires-Dist: zeroconf
